nexios_contrib/__init__.py
nexios_contrib/accepts/README.md
nexios_contrib/accepts/README_DI.md
nexios_contrib/accepts/__init__.py
nexios_contrib/accepts/dependency.py
nexios_contrib/accepts/helpers.py
nexios_contrib/accepts/middleware.py
nexios_contrib/etag/README.md
nexios_contrib/etag/__init__.py
nexios_contrib/etag/helper.py
nexios_contrib/etag/middleware.py
nexios_contrib/graphql/__init__.py
nexios_contrib/graphql/plugin.py
nexios_contrib/jrpc/README.md
nexios_contrib/jrpc/__init__.py
nexios_contrib/jrpc/client.py
nexios_contrib/jrpc/exceptions.py
nexios_contrib/jrpc/registry.py
nexios_contrib/jrpc/server.py
nexios_contrib/proxy/README.md
nexios_contrib/proxy/__init__.py
nexios_contrib/proxy/helper.py
nexios_contrib/proxy/middleware.py
nexios_contrib/redis/README.md
nexios_contrib/redis/__init__.py
nexios_contrib/redis/client.py
nexios_contrib/redis/config.py
nexios_contrib/redis/dependency.py
nexios_contrib/redis/utils.py
nexios_contrib/request_id/README.md
nexios_contrib/request_id/__init__.py
nexios_contrib/request_id/dependency.py
nexios_contrib/request_id/helper.py
nexios_contrib/request_id/middleware.py
nexios_contrib/scalar/__init__.py
nexios_contrib/scalar/plugin.py
nexios_contrib/slashes/README.md
nexios_contrib/slashes/__init__.py
nexios_contrib/slashes/helpers.py
nexios_contrib/slashes/middleware.py
nexios_contrib/tasks/README.md
nexios_contrib/tasks/__init__.py
nexios_contrib/tasks/config.py
nexios_contrib/tasks/dependency.py
nexios_contrib/tasks/manager.py
nexios_contrib/tasks/models.py
nexios_contrib/timeout/README.md
nexios_contrib/timeout/helper.py
nexios_contrib/timeout/middleware.py
nexios_contrib/tortoise/README.md
nexios_contrib/tortoise/__init__.py
nexios_contrib/tortoise/client.py
nexios_contrib/tortoise/config.py
nexios_contrib/tortoise/exceptions.py
nexios_contrib/trusted/README.md
nexios_contrib/trusted/__init__.py
nexios_contrib/trusted/helpers.py
nexios_contrib/trusted/middleware.py
nexios_contrib-0.3.1.dist-info/METADATA
nexios_contrib-0.3.1.dist-info/WHEEL
nexios_contrib-0.3.1.dist-info/licenses/LICENSE
nexios_contrib-0.3.1.dist-info/RECORD
