Metadata-Version: 2.4
Name: nexios_contrib
Version: 0.3.1
Summary: Utility pack for Nexios
Author-email: Chidebele Dunamis <techwithdunamix@gmail.com>
License-Expression: BSD-3-Clause
License-File: LICENSE
Keywords: API,ASGI,HTTP,Python,async,asynchronous,backend,concurrent,framework,granian,real-time,scalable,uvicorn,web,web server,websocket
Requires-Python: >=3.9
Requires-Dist: nexios>=3.0.0
Provides-Extra: all
Requires-Dist: anyio>=4.0.0; extra == 'all'
Requires-Dist: click>=8.1.3; extra == 'all'
Requires-Dist: granian>=1.2.0; extra == 'all'
Requires-Dist: itsdangerous>=2.1.2; extra == 'all'
Requires-Dist: jinja2>=3.1.6; extra == 'all'
Requires-Dist: pyjwt>=2.7.0; extra == 'all'
Requires-Dist: python-multipart>=0.0.6; extra == 'all'
Requires-Dist: redis>=4.0.0; extra == 'all'
Requires-Dist: scalar-docs>=0.1.0; extra == 'all'
Requires-Dist: strawberry-graphql>=0.219.0; extra == 'all'
Requires-Dist: uvicorn>=0.27.0; extra == 'all'
Provides-Extra: dev
Requires-Dist: aiosqlite<0.20.0; extra == 'dev'
Requires-Dist: anyio>=4.0.0; extra == 'dev'
Requires-Dist: black>=23.0.0; extra == 'dev'
Requires-Dist: click>=8.1.3; extra == 'dev'
Requires-Dist: coverage<8.0,>=6.3; extra == 'dev'
Requires-Dist: granian>=1.2.0; extra == 'dev'
Requires-Dist: httpx<0.29.0,>=0.23.3; extra == 'dev'
Requires-Dist: isort>=5.13.2; extra == 'dev'
Requires-Dist: itsdangerous>=2.1.2; extra == 'dev'
Requires-Dist: jinja2>=3.1.6; extra == 'dev'
Requires-Dist: mypy>=1.15.0; extra == 'dev'
Requires-Dist: nexios>=3.2.0; extra == 'dev'
Requires-Dist: pyjwt>=2.7.0; extra == 'dev'
Requires-Dist: pytest-asyncio<0.27.0,>=0.25.3; extra == 'dev'
Requires-Dist: pytest<8.5.0,>=8.3.4; extra == 'dev'
Requires-Dist: python-multipart>=0.0.6; extra == 'dev'
Requires-Dist: redis>=4.0.0; extra == 'dev'
Requires-Dist: ruff>=0.0.256; extra == 'dev'
Requires-Dist: scalar-docs>=0.1.0; extra == 'dev'
Requires-Dist: strawberry-graphql>=0.219.0; extra == 'dev'
Requires-Dist: tortoise-orm>=0.20.0; extra == 'dev'
Requires-Dist: typing-extensions==4.12.2; extra == 'dev'
Requires-Dist: uvicorn>=0.27.0; extra == 'dev'
Provides-Extra: graphql
Requires-Dist: strawberry-graphql>=0.219.0; extra == 'graphql'
Provides-Extra: redis
Requires-Dist: redis>=4.0.0; extra == 'redis'
Provides-Extra: scalar
Requires-Dist: scalar-docs>=0.1.0; extra == 'scalar'
Provides-Extra: templating
Requires-Dist: jinja2>=3.1.6; extra == 'templating'
Provides-Extra: tortoise
Requires-Dist: aiosqlite<0.20.0; extra == 'tortoise'
Requires-Dist: tortoise-orm>=0.20.0; extra == 'tortoise'
